<?xml version="1.0" encoding="UTF-8"?>
<alpino_ds version="1.6">
  <parser cats="1" skips="0" />
  <node begin="0" cat="top" end="26" id="0" rel="top">
    <node begin="0" cat="smain" end="25" id="1" rel="--">
      <node begin="0" cat="np" end="2" id="2" index="1" rel="su">
        <node begin="0" buiging="zonder" end="1" frame="determiner(de,nwh,nmod,pro,nparg)" his="normal" his_1="decap" his_1_1="normal" id="3" infl="de" lcat="detp" lemma="die" naamval="stan" npagr="rest" pdtype="det" pos="det" positie="prenom" postag="VNW(aanw,det,stan,prenom,zonder,rest)" pt="vnw" rel="det" root="die" sense="die" vwtype="aanw" wh="nwh" word="Die"/>
        <node begin="1" end="2" frame="noun(het,count,pl)" gen="het" getal="mv" graad="basis" his="normal" his_1="normal" id="4" lcat="np" lemma="onderzoek" ntype="soort" num="pl" pos="noun" postag="N(soort,mv,basis)" pt="n" rel="hd" rnum="pl" root="onderzoek" sense="onderzoek" word="onderzoeken"/>
      </node>
      <node begin="2" end="3" frame="verb('hebben/zijn',pl,modifier(aux(inf)))" his="normal" his_1="normal" id="5" infl="pl" lcat="smain" lemma="moeten" pos="verb" postag="WW(pv,tgw,mv)" pt="ww" pvagr="mv" pvtijd="tgw" rel="hd" root="moet" sc="modifier(aux(inf))" sense="moet" stype="declarative" tense="present" word="moeten" wvorm="pv"/>
      <node begin="0" cat="inf" end="25" id="6" rel="vc">
        <node begin="0" end="2" id="7" index="1" rel="su"/>
        <node begin="3" buiging="zonder" end="4" frame="verb(hebben,inf,ninv(sbar,part_sbar(uit)))" his="normal" his_1="part-V" id="8" infl="inf" lcat="inf" lemma="uit_wijzen" pos="verb" positie="vrij" postag="WW(inf,vrij,zonder)" pt="ww" rel="hd" root="wijs_uit" sc="part_sbar(uit)" sense="wijs_uit" word="uitwijzen" wvorm="inf"/>
        <node begin="4" cat="whsub" end="25" id="9" rel="vc">
          <node begin="4" case="both" def="indef" end="5" frame="pronoun(ywh,thi,both,de,both,indef)" gen="de" getal="getal" his="normal" his_1="normal" id="10" index="2" lcat="np" lemma="wie" naamval="stan" num="both" pdtype="pron" per="thi" persoon="3p" pos="pron" postag="VNW(vb,pron,stan,vol,3p,getal)" pt="vnw" rel="whd" rnum="sg" root="wie" sense="wie" status="vol" vwtype="vb" wh="ywh" word="wie"/>
          <node begin="4" cat="ssub" end="25" id="11" rel="body">
            <node begin="4" end="5" id="12" index="2" rel="su"/>
            <node begin="5" end="6" frame="adverb" getal="ev" his="normal" his_1="normal" id="13" lcat="advp" lemma="wat" naamval="stan" pdtype="pron" persoon="3o" pos="adv" postag="VNW(onbep,pron,stan,vol,3o,ev)" pt="vnw" rel="mod" root="wat" sense="wat" status="vol" vwtype="onbep" word="wat"/>
            <node begin="6" end="7" frame="verb(hebben,past(sg),tr_sbar)" his="normal" his_1="normal" id="14" infl="sg" lcat="ssub" lemma="weten" pos="verb" postag="WW(pv,verl,ev)" pt="ww" pvagr="ev" pvtijd="verl" rel="hd" root="weet" sc="tr_sbar" sense="weet" tense="past" word="wist" wvorm="pv"/>
            <node begin="7" cat="pp" end="14" id="15" rel="mod">
              <node begin="7" end="8" frame="preposition(binnen,[])" his="normal" his_1="normal" id="16" lcat="pp" lemma="binnen" pos="prep" postag="VZ(init)" pt="vz" rel="hd" root="binnen" sense="binnen" vztype="init" word="binnen"/>
              <node begin="8" cat="np" end="14" id="17" rel="obj1">
                <node begin="8" end="9" frame="determiner(het,nwh,nmod,pro,nparg,wkpro)" his="normal" his_1="normal" id="18" infl="het" lcat="detp" lemma="het" lwtype="bep" naamval="stan" npagr="evon" pos="det" postag="LID(bep,stan,evon)" pt="lid" rel="det" root="het" sense="het" wh="nwh" word="het"/>
                <node begin="9" end="10" frame="noun(het,count,sg)" gen="het" genus="onz" getal="ev" graad="basis" his="normal" his_1="normal" id="19" lcat="np" lemma="leger" naamval="stan" ntype="soort" num="sg" pos="noun" postag="N(soort,ev,basis,onz,stan)" pt="n" rel="hd" rnum="sg" root="leger" sense="leger" word="leger"/>
                <node begin="10" cat="pp" end="14" id="20" rel="mod">
                  <node begin="10" end="11" frame="preposition(over,[heen])" his="normal" his_1="normal" id="21" lcat="pp" lemma="over" pos="prep" postag="VZ(init)" pt="vz" rel="hd" root="over" sense="over" vztype="init" word="over"/>
                  <node begin="11" cat="np" end="14" id="22" rel="obj1">
                    <node begin="11" end="12" frame="determiner(de)" his="normal" his_1="normal" id="23" infl="de" lcat="detp" lemma="de" lwtype="bep" naamval="stan" npagr="rest" pos="det" postag="LID(bep,stan,rest)" pt="lid" rel="det" root="de" sense="de" word="de"/>
                    <node aform="base" begin="12" buiging="met-e" end="13" frame="adjective(e)" graad="basis" his="normal" his_1="normal" id="24" infl="e" lcat="ap" lemma="Amerikaans" naamval="stan" pos="adj" positie="prenom" postag="ADJ(prenom,basis,met-e,stan)" pt="adj" rel="mod" root="Amerikaans" sense="Amerikaans" vform="adj" word="Amerikaanse"/>
                    <node begin="13" end="14" frame="noun(de,count,sg)" gen="de" genus="zijd" getal="ev" graad="basis" his="normal" his_1="normal" id="25" lcat="np" lemma="studie" naamval="stan" ntype="soort" num="sg" pos="noun" postag="N(soort,ev,basis,zijd,stan)" pt="n" rel="hd" rnum="sg" root="studie" sense="studie" word="studie"/>
                  </node>
                </node>
              </node>
            </node>
            <node begin="14" cat="whsub" end="25" id="26" rel="vc">
              <node begin="14" end="15" frame="waar_adverb(uit)" his="normal" his_1="normal" id="27" index="3" lcat="pp" lemma="waaruit" pos="pp" postag="BW()" pt="bw" rel="whd" root="waaruit" sense="waaruit" special="waar" word="waaruit"/>
              <node begin="14" cat="ssub" end="25" id="28" rel="body">
                <node begin="14" end="15" id="29" index="3" rel="pc"/>
                <node begin="15" end="16" frame="verb(unacc,past(sg),pp_sbar_subj_no_het(uit))" his="normal" his_1="normal" id="30" infl="sg" lcat="ssub" lemma="blijken" pos="verb" postag="WW(pv,verl,ev)" pt="ww" pvagr="ev" pvtijd="verl" rel="hd" root="blijk" sc="pp_sbar_subj_no_het(uit)" sense="blijk-uit" tense="past" word="bleek" wvorm="pv"/>
                <node begin="16" cat="cp" end="25" id="31" rel="su">
                  <node begin="16" conjtype="onder" end="17" frame="complementizer(dat)" his="normal" his_1="normal" id="32" lcat="cp" lemma="dat" pos="comp" postag="VG(onder)" pt="vg" rel="cmp" root="dat" sc="dat" sense="dat" word="dat"/>
                  <node begin="17" cat="ssub" end="25" id="33" rel="body">
                    <node begin="17" cat="np" end="19" id="34" index="4" rel="su">
                      <node begin="17" end="18" frame="determiner(de)" his="normal" his_1="normal" id="35" infl="de" lcat="detp" lemma="de" lwtype="bep" naamval="stan" npagr="rest" pos="det" postag="LID(bep,stan,rest)" pt="lid" rel="det" root="de" sense="de" word="de"/>
                      <node begin="18" end="19" frame="noun(de,count,pl)" gen="de" getal="mv" graad="basis" his="normal" his_1="normal" id="36" lcat="np" lemma="F-16" ntype="soort" num="pl" pos="noun" postag="N(soort,mv,basis)" pt="n" rel="hd" rnum="pl" root="F-16" sense="F-16" word="F-16&apos;s"/>
                    </node>
                    <node begin="20" end="21" frame="verb('hebben/zijn',pl,aux(inf))" his="normal" his_1="normal" id="37" infl="pl" lcat="ssub" lemma="kunnen" pos="verb" postag="WW(pv,tgw,mv)" pt="ww" pvagr="mv" pvtijd="tgw" rel="hd" root="kan" sc="aux(inf)" sense="kan" tense="present" word="kunnen" wvorm="pv"/>
                    <node begin="17" cat="inf" end="25" id="38" rel="vc">
                      <node begin="17" end="19" id="39" index="4" rel="su"/>
                      <node begin="21" buiging="zonder" end="22" frame="verb(hebben,inf,intransitive)" his="normal" his_1="normal" id="40" infl="inf" lcat="inf" lemma="vliegen" pos="verb" positie="vrij" postag="WW(inf,vrij,zonder)" pt="ww" rel="hd" root="vlieg" sc="intransitive" sense="vlieg" word="vliegen" wvorm="inf"/>
                      <node begin="19" cat="ap" end="25" id="41" rel="mod">
                        <node aform="compar" begin="19" buiging="zonder" end="20" frame="adjective(er(tmpadv))" graad="comp" his="normal" his_1="normal" id="42" infl="no_e" lcat="ap" lemma="lang" pos="adj" positie="vrij" postag="ADJ(vrij,comp,zonder)" pt="adj" rel="hd" root="lang" sense="lang" vform="adj" word="langer"/>
                        <node begin="22" cat="cp" end="25" id="43" rel="obcomp">
                          <node begin="22" conjtype="onder" end="23" frame="comparative(dan)" his="normal" his_1="normal" id="44" lcat="comparative" lemma="dan" pos="comparative" postag="VG(onder)" pt="vg" rel="cmp" root="dan" sense="dan" word="dan"/>
                          <node begin="23" cat="ssub" end="25" id="45" rel="body">
                            <node begin="23" end="24" frame="verb(unacc,past(sg),passive)" his="normal" his_1="normal" id="46" infl="sg" lcat="ssub" lemma="worden" pos="verb" postag="WW(pv,verl,ev)" pt="ww" pvagr="ev" pvtijd="verl" rel="hd" root="word" sc="passive" sense="word" tense="past" word="werd" wvorm="pv"/>
                            <node begin="24" buiging="zonder" end="25" frame="verb(hebben,psp,ninv(transitive,part_transitive(aan)))" his="normal" his_1="part-V" id="47" infl="psp" lcat="ppart" lemma="aan_nemen" pos="verb" positie="vrij" postag="WW(vd,vrij,zonder)" pt="ww" rel="vc" root="neem_aan" sc="part_transitive(aan)" sense="neem_aan" word="aangenomen" wvorm="vd"/>
                          </node>
                        </node>
                      </node>
                    </node>
                  </node>
                </node>
              </node>
            </node>
          </node>
        </node>
      </node>
    </node>
    <node begin="25" end="26" frame="punct(punt)" his="normal" his_1="normal" id="48" lcat="punct" lemma="." pos="punct" postag="LET()" pt="let" rel="--" root="." sense="." special="punt" word="."/>
  </node>
  <sentence sentid="3">Die onderzoeken moeten uitwijzen wie wat wist binnen het leger over de Amerikaanse studie waaruit bleek dat de F-16&apos;s langer kunnen vliegen dan werd aangenomen .</sentence>
  <comments>
    <comment>Q#3|Die onderzoeken moeten uitwijzen wie wat wist binnen het leger over de Amerikaanse studie waaruit bleek dat de F-16&apos;s langer kunnen vliegen dan werd aangenomen .|1|1|-24.04307106162999</comment>
  </comments>
</alpino_ds>
