<?xml version="1.0" encoding="UTF-8"?>
<alpino_ds version="1.6">
  <parser cats="1" skips="0" />
  <node begin="0" cat="top" end="5" id="0" rel="top">
    <node begin="0" cat="smain" end="5" id="1" rel="--">
      <node begin="0" end="1" frame="proper_name(sg,'LOC')" genus="onz" getal="ev" graad="basis" his="normal" his_1="names_dictionary" id="2" lcat="np" lemma="Ierland" naamval="stan" neclass="LOC" ntype="eigen" num="sg" pos="name" postag="N(eigen,ev,basis,onz,stan)" pt="n" rel="su" rnum="sg" root="Ierland" sense="Ierland" word="Ierland"/>
      <node begin="1" end="2" frame="verb(hebben,sg3,transitive)" his="normal" his_1="normal" id="3" infl="sg3" lcat="smain" lemma="organiseren" pos="verb" postag="WW(pv,tgw,met-t)" pt="ww" pvagr="met-t" pvtijd="tgw" rel="hd" root="organiseer" sc="transitive" sense="organiseer" stype="declarative" tense="present" word="organiseert" wvorm="pv"/>
      <node begin="2" cat="np" end="5" id="4" rel="obj1">
        <node begin="2" end="3" frame="noun(het,count,sg)" gen="het" genus="onz" getal="ev" graad="basis" his="normal" his_1="normal" id="5" lcat="np" lemma="referendum" naamval="stan" ntype="soort" num="sg" pos="noun" postag="N(soort,ev,basis,onz,stan)" pt="n" rel="hd" rnum="sg" root="referendum" sense="referendum" word="referendum"/>
        <node begin="3" cat="pp" end="5" id="6" rel="mod">
          <node begin="3" end="4" frame="preposition(over,[heen])" his="normal" his_1="normal" id="7" lcat="pp" lemma="over" pos="prep" postag="VZ(init)" pt="vz" rel="hd" root="over" sense="over" vztype="init" word="over"/>
          <node begin="4" end="5" frame="noun(de,both,sg)" gen="de" genus="zijd" getal="ev" graad="basis" his="normal" his_1="normal" id="8" lcat="np" lemma="abortus" naamval="stan" ntype="soort" num="sg" pos="noun" postag="N(soort,ev,basis,zijd,stan)" pt="n" rel="obj1" rnum="sg" root="abortus" sense="abortus" word="abortus"/>
        </node>
      </node>
    </node>
  </node>
  <sentence sentid="1">Ierland organiseert referendum over abortus</sentence>
  <comments>
    <comment>Q#1|Ierland organiseert referendum over abortus|1|1|-2.2589980413800004</comment>
  </comments>
</alpino_ds>
