<?xml version="1.0" encoding="UTF-8"?>
<alpino_ds version="1.6">
  <parser cats="3" skips="0" />
  <node begin="0" cat="top" end="51" id="0" rel="top">
    <node begin="2" end="3" frame="punct(komma)" his="normal" his_1="normal" id="1" lcat="punct" lemma="," pos="punct" postag="LET()" pt="let" rel="--" root="," sense="," special="komma" word=","/>
    <node begin="11" end="12" frame="punct(komma)" his="normal" his_1="normal" id="2" lcat="punct" lemma="," pos="punct" postag="LET()" pt="let" rel="--" root="," sense="," special="komma" word=","/>
    <node begin="24" end="25" frame="punct(komma)" his="normal" his_1="normal" id="3" lcat="punct" lemma="," pos="punct" postag="LET()" pt="let" rel="--" root="," sense="," special="komma" word=","/>
    <node begin="0" cat="du" end="50" id="4" rel="--">
      <node begin="0" cat="smain" end="35" id="5" rel="dp">
        <node begin="0" cat="np" end="24" id="6" index="1" rel="su">
          <node begin="0" cat="mwu" end="2" his="name" his_1="begin" id="7" mwu_root="Tarik Jadaoun" mwu_sense="Tarik Jadaoun" rel="hd">
            <node begin="0" end="1" frame="proper_name(sg,'PER')" id="8" lcat="np" lemma="Tarik" neclass="PER" num="sg" pos="name" postag="SPEC(deeleigen)" pt="spec" rel="mwp" rnum="sg" root="Tarik" sense="Tarik" spectype="deeleigen" word="Tarik"/>
            <node begin="1" end="2" frame="proper_name(sg,'PER')" id="9" lcat="np" lemma="Jadaoun" neclass="PER" num="sg" pos="name" postag="SPEC(deeleigen)" pt="spec" rel="mwp" rnum="sg" root="Jadaoun" sense="Jadaoun" spectype="deeleigen" word="Jadaoun"/>
          </node>
          <node begin="3" cat="smain" end="24" id="10" rel="mod">
            <node begin="8" end="9" frame="verb(unacc,sg_heeft,ld_pp)" his="special" his_1="decap" his_1_1="normal" id="11" infl="sg_heeft" lcat="smain" lemma="zijn" pos="verb" postag="WW(pv,tgw,ev)" pt="ww" pvagr="ev" pvtijd="tgw" rel="hd" root="ben" sc="ld_pp" sense="ben" stype="declarative" tense="present" word="IS" wvorm="pv"/>
            <node begin="9" cat="pp" end="11" id="12" rel="ld">
              <node begin="9" end="10" frame="preposition(uit,[vandaan])" his="normal" his_1="normal" id="13" lcat="pp" lemma="uit" pos="prep" postag="VZ(init)" pt="vz" rel="hd" root="uit" sense="uit" vztype="init" word="uit"/>
              <node begin="10" end="11" frame="proper_name(sg,'LOC')" genus="onz" getal="ev" graad="basis" his="normal" his_1="names_dictionary" id="14" lcat="np" lemma="Verviers" naamval="stan" neclass="LOC" ntype="eigen" num="sg" pos="name" postag="N(eigen,ev,basis,onz,stan)" pt="n" rel="obj1" rnum="sg" root="Verviers" sense="Verviers" word="Verviers"/>
            </node>
            <node begin="3" cat="np" end="24" id="15" rel="su">
              <node begin="3" end="4" frame="determiner(de)" his="normal" his_1="normal" id="16" infl="de" lcat="detp" lemma="de" lwtype="bep" naamval="stan" npagr="rest" pos="det" postag="LID(bep,stan,rest)" pt="lid" rel="det" root="de" sense="de" word="de"/>
              <node aform="base" begin="4" buiging="met-e" end="5" frame="adjective(ge_e)" his="compound" his_1="2" id="17" infl="e" lcat="ppart" lemma="dood_gewaand" pos="adj" positie="prenom" postag="WW(vd,prenom,met-e)" pt="ww" rel="mod" root="dood_gewaand" sense="dood_gewaand" vform="psp" word="doodgewaande" wvorm="vd"/>
              <node begin="5" end="6" frame="noun(both,both,both)" gen="both" genus="zijd" getal="ev" graad="basis" his="noun" id="18" lcat="np" lemma="jihadi" naamval="stan" ntype="soort" num="both" pos="noun" postag="N(soort,ev,basis,zijd,stan)" pt="n" rel="hd" rnum="sg" root="jihadi" sense="jihadi" word="jihadi"/>
              <node begin="6" cat="pp" end="24" id="19" rel="mod">
                <node begin="6" end="7" frame="preposition(van,[af,uit,vandaan,[af,aan]])" his="normal" his_1="normal" id="20" lcat="pp" lemma="van" pos="prep" postag="VZ(init)" pt="vz" rel="hd" root="van" sense="van" vztype="init" word="van"/>
                <node begin="7" cat="np" end="24" id="21" rel="obj1">
                  <node begin="7" end="8" frame="noun(de,count,sg)" gen="de" genus="zijd" getal="ev" graad="basis" his="normal" his_1="normal" id="22" lcat="np" lemma="terreur_groep" naamval="stan" ntype="soort" num="sg" pos="noun" postag="N(soort,ev,basis,zijd,stan)" pt="n" rel="hd" rnum="sg" root="terreur_groep" sense="terreur_groep" word="terreurgroep"/>
                  <node begin="12" cat="rel" end="24" id="23" rel="mod">
                    <node begin="12" case="no_obl" end="13" frame="rel_pronoun(de,no_obl)" gen="de" getal="getal" his="normal" his_1="normal" id="24" index="2" lcat="np" lemma="die" naamval="stan" pdtype="pron" persoon="persoon" pos="pron" postag="VNW(betr,pron,stan,vol,persoon,getal)" pt="vnw" rel="rhd" rnum="sg" root="die" sense="die" status="vol" vwtype="betr" wh="rel" word="die"/>
                    <node begin="12" cat="ssub" end="24" id="25" rel="body">
                      <node begin="12" end="13" id="26" index="2" rel="su"/>
                      <node begin="13" end="14" frame="verb(unacc,past(sg),passive)" his="normal" his_1="normal" id="27" infl="sg" lcat="ssub" lemma="worden" pos="verb" postag="WW(pv,verl,ev)" pt="ww" pvagr="ev" pvtijd="verl" rel="hd" root="word" sc="passive" sense="word" tense="past" word="werd" wvorm="pv"/>
                      <node begin="12" cat="ppart" end="24" id="28" rel="vc">
                        <node begin="12" end="13" id="29" index="2" rel="obj1"/>
                        <node begin="14" buiging="zonder" end="15" frame="particle(gevangen)" his="normal" his_1="normal" id="30" lcat="part" lemma="gevangen" pos="part" positie="vrij" postag="WW(vd,vrij,zonder)" pt="ww" rel="svp" root="gevangen" sense="gevangen" word="gevangen" wvorm="vd"/>
                        <node begin="15" buiging="zonder" end="16" frame="verb(hebben,psp,part_transitive(gevangen))" his="normal" his_1="normal" id="31" infl="psp" lcat="ppart" lemma="gevangen_nemen" pos="verb" positie="vrij" postag="WW(vd,vrij,zonder)" pt="ww" rel="hd" root="neem_gevangen" sc="part_transitive(gevangen)" sense="neem_gevangen" word="genomen" wvorm="vd"/>
                        <node begin="16" cat="pp" end="24" id="32" rel="mod">
                          <node begin="16" end="17" frame="preposition(bij,[vandaan])" his="normal" his_1="normal" id="33" lcat="pp" lemma="bij" pos="prep" postag="VZ(init)" pt="vz" rel="hd" root="bij" sense="bij" vztype="init" word="bij"/>
                          <node begin="17" cat="np" end="24" id="34" rel="obj1">
                            <node begin="17" end="18" frame="determiner(de)" his="normal" his_1="normal" id="35" infl="de" lcat="detp" lemma="de" lwtype="bep" naamval="stan" npagr="rest" pos="det" postag="LID(bep,stan,rest)" pt="lid" rel="det" root="de" sense="de" word="de"/>
                            <node begin="18" end="19" frame="noun(de,count,sg)" gen="de" genus="zijd" getal="ev" graad="basis" his="normal" his_1="normal" id="36" lcat="np" lemma="strijd" naamval="stan" ntype="soort" num="sg" pos="noun" postag="N(soort,ev,basis,zijd,stan)" pt="n" rel="hd" rnum="sg" root="strijd" sense="strijd" word="strijd"/>
                            <node begin="19" cat="pp" end="24" id="37" rel="mod">
                              <node begin="19" end="20" frame="preposition(om,[heen])" his="normal" his_1="normal" id="38" lcat="pp" lemma="om" pos="prep" postag="VZ(init)" pt="vz" rel="hd" root="om" sense="om" vztype="init" word="om"/>
                              <node begin="20" cat="np" end="24" id="39" rel="obj1">
                                <node begin="20" end="21" frame="determiner(de)" his="normal" his_1="normal" id="40" infl="de" lcat="detp" lemma="de" lwtype="bep" naamval="stan" npagr="rest" pos="det" postag="LID(bep,stan,rest)" pt="lid" rel="det" root="de" sense="de" word="de"/>
                                <node aform="base" begin="21" buiging="met-e" end="22" frame="adjective(e)" graad="basis" his="normal" his_1="normal" id="41" infl="e" lcat="ap" lemma="Iraaks" naamval="stan" pos="adj" positie="prenom" postag="ADJ(prenom,basis,met-e,stan)" pt="adj" rel="mod" root="Iraaks" sense="Iraaks" vform="adj" word="Iraakse"/>
                                <node begin="22" end="23" frame="noun(both,count,sg)" gen="both" genus="zijd" getal="ev" graad="basis" his="normal" his_1="normal" id="42" lcat="np" lemma="stad" naamval="stan" ntype="soort" num="sg" pos="noun" postag="N(soort,ev,basis,zijd,stan)" pt="n" rel="hd" rnum="sg" root="stad" sense="stad" word="stad"/>
                                <node begin="23" end="24" frame="proper_name(both,'LOC')" genus="onz" getal="ev" graad="basis" his="name" his_1="not_begin" id="43" lcat="np" lemma="Mosul" naamval="stan" neclass="LOC" ntype="eigen" num="both" pos="name" postag="N(eigen,ev,basis,onz,stan)" pt="n" rel="app" root="Mosul" sense="Mosul" word="Mosul"/>
                              </node>
                            </node>
                          </node>
                        </node>
                      </node>
                    </node>
                  </node>
                </node>
              </node>
            </node>
          </node>
        </node>
        <node begin="25" end="26" frame="verb(hebben,sg_heeft,aux_psp_hebben)" his="normal" his_1="normal" id="44" infl="sg_heeft" lcat="smain" lemma="hebben" pos="verb" postag="WW(pv,tgw,met-t)" pt="ww" pvagr="met-t" pvtijd="tgw" rel="hd" root="heb" sc="aux_psp_hebben" sense="heb" stype="declarative" tense="present" word="heeft" wvorm="pv"/>
        <node begin="0" cat="ppart" end="35" id="45" rel="vc">
          <node begin="0" end="24" id="46" index="1" rel="su"/>
          <node begin="26" cat="pp" end="33" id="47" rel="mod">
            <node begin="26" end="27" frame="preposition(in,[])" his="normal" his_1="normal" id="48" lcat="pp" lemma="in" pos="prep" postag="VZ(init)" pt="vz" rel="hd" root="in" sense="in" vztype="init" word="in"/>
            <node begin="27" cat="np" end="33" id="49" rel="obj1">
              <node begin="27" end="28" frame="determiner(een)" his="normal" his_1="normal" id="50" infl="een" lcat="detp" lemma="een" lwtype="onbep" naamval="stan" npagr="agr" pos="det" postag="LID(onbep,stan,agr)" pt="lid" rel="det" root="een" sense="een" word="een"/>
              <node begin="28" end="29" frame="noun(het,count,sg)" gen="het" genus="onz" getal="ev" graad="basis" his="normal" his_1="normal" id="51" lcat="np" lemma="verhoor" naamval="stan" ntype="soort" num="sg" pos="noun" postag="N(soort,ev,basis,onz,stan)" pt="n" rel="hd" rnum="sg" root="verhoor" sense="verhoor" word="verhoor"/>
              <node begin="29" cat="pp" end="33" id="52" rel="mod">
                <node begin="29" end="30" frame="preposition(door,[heen])" his="normal" his_1="normal" id="53" lcat="pp" lemma="door" pos="prep" postag="VZ(init)" pt="vz" rel="hd" root="door" sense="door" vztype="init" word="door"/>
                <node begin="30" cat="np" end="33" id="54" rel="obj1">
                  <node begin="30" end="31" frame="determiner(het,nwh,nmod,pro,nparg,wkpro)" his="normal" his_1="normal" id="55" infl="het" lcat="detp" lemma="het" lwtype="bep" naamval="stan" npagr="evon" pos="det" postag="LID(bep,stan,evon)" pt="lid" rel="det" root="het" sense="het" wh="nwh" word="het"/>
                  <node aform="base" begin="31" buiging="met-e" end="32" frame="adjective(e)" graad="basis" his="normal" his_1="normal" id="56" infl="e" lcat="ap" lemma="Iraaks" naamval="stan" pos="adj" positie="prenom" postag="ADJ(prenom,basis,met-e,stan)" pt="adj" rel="mod" root="Iraaks" sense="Iraaks" vform="adj" word="Iraakse"/>
                  <node begin="32" end="33" frame="noun(het,count,sg)" gen="het" genus="onz" getal="ev" graad="basis" his="normal" his_1="normal" id="57" lcat="np" lemma="gerecht" naamval="stan" ntype="soort" num="sg" pos="noun" postag="N(soort,ev,basis,onz,stan)" pt="n" rel="hd" rnum="sg" root="gerecht" sense="gerecht" word="gerecht"/>
                </node>
              </node>
            </node>
          </node>
          <node begin="33" buiging="zonder" end="34" frame="verb(hebben,psp,sbar)" his="normal" his_1="normal" id="58" infl="psp" lcat="ppart" lemma="vertellen" pos="verb" positie="vrij" postag="WW(vd,vrij,zonder)" pt="ww" rel="hd" root="vertel" sc="sbar" sense="vertel" word="verteld" wvorm="vd"/>
          <node begin="34" end="35" frame="wh_adjective" his="normal" his_1="normal" id="59" lcat="ap" lemma="hoe" pos="adj" postag="BW()" pt="bw" rel="vc" root="hoe" sense="hoe" stype="whquestion" wh="ywh" word="hoe"/>
        </node>
      </node>
      <node begin="35" case="nom" def="def" end="36" frame="pronoun(nwh,thi,sg,de,nom,def)" gen="de" genus="masc" getal="ev" his="normal" his_1="normal" id="60" lcat="np" lemma="hij" naamval="nomin" num="sg" pdtype="pron" per="thi" persoon="3" pos="pron" postag="VNW(pers,pron,nomin,vol,3,ev,masc)" pt="vnw" rel="dp" rnum="sg" root="hij" sense="hij" status="vol" vwtype="pers" wh="nwh" word="hij"/>
      <node begin="36" cat="du" end="50" id="61" rel="dp">
        <node begin="36" cat="pp" end="40" id="62" rel="dp">
          <node begin="36" end="37" frame="preposition(van,[af,uit,vandaan,[af,aan]])" his="normal" his_1="normal" id="63" lcat="pp" lemma="van" pos="prep" postag="VZ(init)" pt="vz" rel="hd" root="van" sense="van" vztype="init" word="van"/>
          <node begin="37" cat="np" end="40" id="64" rel="obj1">
            <node begin="37" end="38" frame="determiner(een)" his="normal" his_1="normal" id="65" infl="een" lcat="detp" lemma="een" lwtype="onbep" naamval="stan" npagr="agr" pos="det" postag="LID(onbep,stan,agr)" pt="lid" rel="det" root="een" sense="een" word="een"/>
            <node aform="base" begin="38" buiging="met-e" end="39" frame="adjective(e)" graad="basis" his="normal" his_1="normal" id="66" infl="e" lcat="ap" lemma="simpel" naamval="stan" pos="adj" positie="prenom" postag="ADJ(prenom,basis,met-e,stan)" pt="adj" rel="mod" root="simpel" sense="simpel" vform="adj" word="simpele"/>
            <node begin="39" end="40" frame="noun(de,count,sg)" gen="de" genus="zijd" getal="ev" graad="basis" his="normal" his_1="normal" id="67" lcat="np" lemma="overvaller" naamval="stan" ntype="soort" num="sg" pos="noun" postag="N(soort,ev,basis,zijd,stan)" pt="n" rel="hd" rnum="sg" root="overvaller" sense="overvaller" word="overvaller"/>
          </node>
        </node>
        <node begin="40" cat="np" end="50" id="68" rel="dp">
          <node aform="base" begin="40" buiging="met-e" end="41" frame="adjective(ge_e)" getal-n="zonder-n" his="normal" his_1="normal" id="69" infl="e" lcat="np" lemma="uitgegroeid" pos="adj" positie="nom" postag="WW(vd,nom,met-e,zonder-n)" pt="ww" rel="hd" rnum="sg" root="uitgegroeid" sense="uitgegroeid" vform="psp" word="uitgegroeide" wvorm="vd"/>
          <node begin="41" cat="pp" end="50" id="70" rel="mod">
            <node begin="41" end="42" frame="preposition(tot,[toe,[aan,toe]])" his="normal" his_1="normal" id="71" lcat="pp" lemma="tot" pos="prep" postag="VZ(init)" pt="vz" rel="hd" root="tot" sense="tot" vztype="init" word="tot"/>
            <node begin="42" cat="np" end="50" id="72" rel="obj1">
              <node begin="42" end="43" frame="determiner(de)" his="normal" his_1="normal" id="73" infl="de" lcat="detp" lemma="de" lwtype="bep" naamval="stan" npagr="rest" pos="det" postag="LID(bep,stan,rest)" pt="lid" rel="det" root="de" sense="de" word="de"/>
              <node begin="43" cat="ppart" end="45" id="74" rel="mod">
                <node aform="super" begin="43" buiging="zonder" end="44" frame="adjective(st(adv))" graad="sup" his="normal" his_1="normal" id="75" infl="no_e" lcat="ap" lemma="meest" naamval="stan" pdtype="grad" pos="adj" positie="vrij" postag="VNW(onbep,grad,stan,vrij,zonder,sup)" pt="vnw" rel="mod" root="meest" sense="meest" vform="adj" vwtype="onbep" word="meest"/>
                <node aform="base" begin="44" buiging="met-e" end="45" frame="adjective(ge_e)" his="normal" his_1="normal" id="76" infl="e" lcat="ppart" lemma="gevreesd" pos="adj" positie="prenom" postag="WW(vd,prenom,met-e)" pt="ww" rel="hd" root="gevreesd" sense="gevreesd" vform="psp" word="gevreesde" wvorm="vd"/>
              </node>
              <node begin="45" end="46" frame="noun(both,both,both)" gen="both" genus="zijd" getal="ev" graad="basis" his="noun" id="77" lcat="np" lemma="jihadi" naamval="stan" ntype="soort" num="both" pos="noun" postag="N(soort,ev,basis,zijd,stan)" pt="n" rel="hd" rnum="sg" root="jihadi" sense="jihadi" word="jihadi"/>
              <node begin="46" cat="pp" end="50" id="78" rel="mod">
                <node begin="46" end="47" frame="preposition(van,[af,uit,vandaan,[af,aan]])" his="normal" his_1="normal" id="79" lcat="pp" lemma="van" pos="prep" postag="VZ(init)" pt="vz" rel="hd" root="van" sense="van" vztype="init" word="van"/>
                <node begin="47" cat="np" end="50" id="80" rel="obj1">
                  <node begin="47" end="48" frame="determiner(de)" his="normal" his_1="normal" id="81" infl="de" lcat="detp" lemma="de" lwtype="bep" naamval="stan" npagr="rest" pos="det" postag="LID(bep,stan,rest)" pt="lid" rel="det" root="de" sense="de" word="de"/>
                  <node aform="base" begin="48" buiging="met-e" end="49" frame="adjective(e)" graad="basis" his="normal" his_1="normal" id="82" infl="e" lcat="ap" lemma="Belgisch" naamval="stan" pos="adj" positie="prenom" postag="ADJ(prenom,basis,met-e,stan)" pt="adj" rel="mod" root="Belgisch" sense="Belgisch" vform="adj" word="Belgische"/>
                  <node begin="49" end="50" frame="noun(de,count,pl)" gen="de" getal="mv" graad="basis" his="compound" his_1="hyphen" id="83" lcat="np" lemma="IS_strijder" ntype="soort" num="pl" pos="noun" postag="N(soort,mv,basis)" pt="n" rel="hd" rnum="pl" root="IS_strijder" sense="IS_strijder" word="IS-strijders"/>
                </node>
              </node>
            </node>
          </node>
        </node>
      </node>
    </node>
    <node begin="50" end="51" frame="punct(punt)" his="robust_skip" id="84" lcat="--" lemma="." pos="punct" postag="LET()" pt="let" rel="--" root="." sense="." special="punt" word="."/>
  </node>
  <sentence sentid="2">Tarik Jadaoun , de doodgewaande jihadi van terreurgroep IS uit Verviers , die werd gevangen genomen bij de strijd om de Iraakse stad Mosul , heeft in een verhoor door het Iraakse gerecht verteld hoe hij van een simpele overvaller uitgegroeide tot de meest gevreesde jihadi van de Belgische IS-strijders .</sentence>
  <comments>
    <comment>Q#2|Tarik Jadaoun , de doodgewaande jihadi van terreurgroep IS uit Verviers , die werd gevangen genomen bij de strijd om de Iraakse stad Mosul , heeft in een verhoor door het Iraakse gerecht verteld hoe hij van een simpele overvaller uitgegroeide tot de meest gevreesde jihadi van de Belgische IS-strijders .|1|3|-9.378969892189959</comment>
  </comments>
</alpino_ds>
