<?xml version="1.0" encoding="UTF-8"?>
<alpino_ds version="1.6">
  <parser cats="1" skips="0" />
  <node begin="0" cat="top" end="29" id="0" rel="top">
    <node begin="9" end="10" frame="punct(komma)" his="normal" his_1="normal" id="1" lcat="punct" lemma="," pos="punct" postag="LET()" pt="let" rel="--" root="," sense="," special="komma" word=","/>
    <node begin="16" end="17" frame="punct(komma)" his="normal" his_1="normal" id="2" lcat="punct" lemma="," pos="punct" postag="LET()" pt="let" rel="--" root="," sense="," special="komma" word=","/>
    <node begin="0" cat="du" end="28" id="3" rel="--">
      <node begin="0" cat="smain" end="16" id="4" rel="nucl">
        <node begin="10" end="11" frame="verb('hebben/zijn',modal_not_u,aux(inf))" his="normal" his_1="normal" id="5" infl="modal_not_u" lcat="smain" lemma="kunnen" pos="verb" postag="WW(pv,tgw,ev)" pt="ww" pvagr="ev" pvtijd="tgw" rel="hd" root="kan" sc="aux(inf)" sense="kan" stype="declarative" tense="present" word="kan" wvorm="pv"/>
        <node begin="11" cat="np" end="13" id="6" index="1" rel="su">
          <node begin="11" buiging="met-e" end="12" frame="determiner(onze)" getal="mv" his="normal" his_1="normal" id="7" infl="onze" lcat="detp" lemma="ons" naamval="stan" npagr="rest" pdtype="det" persoon="1" pos="det" positie="prenom" postag="VNW(bez,det,stan,vol,1,mv,prenom,met-e,rest)" pt="vnw" rel="det" root="ons" sense="ons" status="vol" vwtype="bez" word="onze"/>
          <node begin="12" end="13" frame="noun(de,mass,sg)" gen="de" genus="zijd" getal="ev" graad="basis" his="normal" his_1="normal" id="8" lcat="np" lemma="samenwerking" naamval="stan" ntype="soort" num="sg" pos="noun" postag="N(soort,ev,basis,zijd,stan)" pt="n" rel="hd" rnum="sg" root="samenwerking" sense="samenwerking" word="samenwerking"/>
        </node>
        <node begin="0" cat="inf" end="16" id="9" rel="vc">
          <node begin="0" cat="cp" end="9" id="10" rel="mod">
            <node begin="0" conjtype="onder" end="1" frame="complementizer(als)" his="normal" his_1="decap" his_1_1="normal" id="11" lcat="cp" lemma="als" pos="comp" postag="VG(onder)" pt="vg" rel="cmp" root="als" sc="als" sense="als" word="Als"/>
            <node begin="1" cat="ssub" end="9" id="12" rel="body">
              <node begin="1" cat="np" end="3" id="13" rel="su">
                <node begin="1" end="2" frame="determiner(de)" his="normal" his_1="normal" id="14" infl="de" lcat="detp" lemma="de" lwtype="bep" naamval="stan" npagr="rest" pos="det" postag="LID(bep,stan,rest)" pt="lid" rel="det" root="de" sense="de" word="de"/>
                <node begin="2" end="3" frame="noun(both,both,both)" gen="both" genus="zijd" getal="ev" graad="basis" his="noun" id="15" lcat="np" lemma="regering-Trump" naamval="stan" ntype="soort" num="both" pos="noun" postag="N(soort,ev,basis,zijd,stan)" pt="n" rel="hd" rnum="sg" root="regering-Trump" sense="regering-Trump" word="regering-Trump"/>
              </node>
              <node begin="3" cat="np" end="7" id="16" rel="obj1">
                <node begin="3" end="4" frame="determiner(de)" his="normal" his_1="normal" id="17" infl="de" lcat="detp" lemma="de" lwtype="bep" naamval="stan" npagr="rest" pos="det" postag="LID(bep,stan,rest)" pt="lid" rel="det" root="de" sense="de" word="de"/>
                <node begin="4" end="5" frame="noun(de,mass,sg)" gen="de" genus="zijd" getal="ev" graad="basis" his="normal" his_1="normal" id="18" lcat="np" lemma="soevereiniteit" naamval="stan" ntype="soort" num="sg" pos="noun" postag="N(soort,ev,basis,zijd,stan)" pt="n" rel="hd" rnum="sg" root="soevereiniteit" sense="soevereiniteit" word="soevereiniteit"/>
                <node begin="5" cat="pp" end="7" id="19" rel="mod">
                  <node begin="5" end="6" frame="preposition(van,[af,uit,vandaan,[af,aan]])" his="normal" his_1="normal" id="20" lcat="pp" lemma="van" pos="prep" postag="VZ(init)" pt="vz" rel="hd" root="van" sense="van" vztype="init" word="van"/>
                  <node begin="6" end="7" frame="proper_name(sg,'LOC')" genus="onz" getal="ev" graad="basis" his="normal" his_1="names_dictionary" id="21" lcat="np" lemma="Turkije" naamval="stan" neclass="LOC" ntype="eigen" num="sg" pos="name" postag="N(eigen,ev,basis,onz,stan)" pt="n" rel="obj1" rnum="sg" root="Turkije" sense="Turkije" word="Turkije"/>
                </node>
              </node>
              <node begin="7" end="8" frame="adverb" his="normal" his_1="normal" id="22" lcat="advp" lemma="niet" pos="adv" postag="BW()" pt="bw" rel="mod" root="niet" sense="niet" word="niet"/>
              <node begin="8" end="9" frame="verb(hebben,sg3,transitive)" his="normal" his_1="normal" id="23" infl="sg3" lcat="ssub" lemma="respecteren" pos="verb" postag="WW(pv,tgw,met-t)" pt="ww" pvagr="met-t" pvtijd="tgw" rel="hd" root="respecteer" sc="transitive" sense="respecteer" tense="present" word="respecteert" wvorm="pv"/>
            </node>
          </node>
          <node begin="11" end="13" id="24" index="1" rel="su"/>
          <node begin="13" cat="pp" end="15" id="25" rel="predc">
            <node begin="13" end="14" frame="preposition(in,[])" his="normal" his_1="normal" id="26" lcat="pp" lemma="in" pos="prep" postag="VZ(init)" pt="vz" rel="hd" root="in" sense="in" vztype="init" word="in"/>
            <node begin="14" end="15" frame="noun(het,count,sg,pred_pp(in))" gen="het" genus="onz" getal="ev" graad="basis" his="normal" his_1="normal" id="27" lcat="np" lemma="gevaar" naamval="stan" ntype="soort" num="sg" pos="noun" postag="N(soort,ev,basis,onz,stan)" pt="n" rel="obj1" rnum="sg" root="gevaar" sc="pred_pp(in)" sense="gevaar" word="gevaar"/>
          </node>
          <node begin="15" buiging="zonder" end="16" frame="verb(unacc,inf,copula)" his="normal" his_1="normal" id="28" infl="inf" lcat="inf" lemma="zijn" pos="verb" positie="vrij" postag="WW(inf,vrij,zonder)" pt="ww" rel="hd" root="ben" sc="copula" sense="ben" word="zijn" wvorm="inf"/>
        </node>
      </node>
      <node begin="17" cat="sv1" end="28" id="29" rel="tag">
        <node begin="17" end="18" frame="verb(hebben,past(sg),sbar)" his="normal" his_1="normal" id="30" infl="sg" lcat="sv1" lemma="schrijven" pos="verb" postag="WW(pv,verl,ev)" pt="ww" pvagr="ev" pvtijd="verl" rel="hd" root="schrijf" sc="sbar" sense="schrijf" tense="past" word="schreef" wvorm="pv"/>
        <node begin="18" end="19" frame="proper_name(sg,'PER')" genus="zijd" getal="ev" graad="basis" his="normal" his_1="names_dictionary" id="31" lcat="np" lemma="Erdogan" naamval="stan" neclass="PER" ntype="eigen" num="sg" pos="name" postag="N(eigen,ev,basis,zijd,stan)" pt="n" rel="su" rnum="sg" root="Erdogan" sense="Erdogan" word="Erdogan"/>
        <node begin="19" end="20" frame="tmp_noun(de,count,sg)" gen="de" genus="zijd" getal="ev" graad="basis" his="normal" his_1="normal" id="32" lcat="np" lemma="vrijdag_avond" naamval="stan" ntype="soort" num="sg" pos="noun" postag="N(soort,ev,basis,zijd,stan)" pt="n" rel="mod" rnum="sg" root="vrijdag_avond" sense="vrijdag_avond" special="tmp" word="vrijdagavond"/>
        <node begin="20" cat="pp" end="23" id="33" rel="mod">
          <node begin="20" end="21" frame="preposition(in,[])" his="normal" his_1="normal" id="34" lcat="pp" lemma="in" pos="prep" postag="VZ(init)" pt="vz" rel="hd" root="in" sense="in" vztype="init" word="in"/>
          <node begin="21" cat="np" end="23" id="35" rel="obj1">
            <node begin="21" end="22" frame="determiner(een)" his="normal" his_1="normal" id="36" infl="een" lcat="detp" lemma="een" lwtype="onbep" naamval="stan" npagr="agr" pos="det" postag="LID(onbep,stan,agr)" pt="lid" rel="det" root="een" sense="een" word="een"/>
            <node begin="22" end="23" frame="noun(de,count,sg)" gen="de" genus="zijd" getal="ev" graad="basis" his="compound" his_1="2" id="37" lcat="np" lemma="gast_bijdrage" naamval="stan" ntype="soort" num="sg" pos="noun" postag="N(soort,ev,basis,zijd,stan)" pt="n" rel="hd" rnum="sg" root="gast_bijdrage" sense="gast_bijdrage" word="gastbijdrage"/>
          </node>
        </node>
        <node begin="23" cat="pp" end="28" id="38" rel="mod">
          <node begin="23" end="24" frame="preposition(in,[])" his="normal" his_1="normal" id="39" lcat="pp" lemma="in" pos="prep" postag="VZ(init)" pt="vz" rel="hd" root="in" sense="in" vztype="init" word="in"/>
          <node begin="24" cat="np" end="28" id="40" rel="obj1">
            <node begin="24" end="25" frame="determiner(de)" his="normal" his_1="normal" id="41" infl="de" lcat="detp" lemma="de" lwtype="bep" naamval="stan" npagr="rest" pos="det" postag="LID(bep,stan,rest)" pt="lid" rel="det" root="de" sense="de" word="de"/>
            <node begin="25" cat="mwu" end="28" his="normal" his_1="names_dictionary" id="42" mwu_root="New York Times" mwu_sense="New York Times" rel="hd">
              <node begin="25" end="26" frame="proper_name(sg,'ORG')" id="43" lcat="np" lemma="New" neclass="ORG" num="sg" pos="name" postag="SPEC(deeleigen)" pt="spec" rel="mwp" rnum="sg" root="New" sense="New" spectype="deeleigen" word="New"/>
              <node begin="26" end="27" frame="proper_name(sg,'ORG')" id="44" lcat="np" lemma="York" neclass="ORG" num="sg" pos="name" postag="SPEC(deeleigen)" pt="spec" rel="mwp" rnum="sg" root="York" sense="York" spectype="deeleigen" word="York"/>
              <node begin="27" end="28" frame="proper_name(sg,'ORG')" id="45" lcat="np" lemma="Times" neclass="ORG" num="sg" pos="name" postag="SPEC(deeleigen)" pt="spec" rel="mwp" rnum="sg" root="Times" sense="Times" spectype="deeleigen" word="Times"/>
            </node>
          </node>
        </node>
      </node>
    </node>
    <node begin="28" end="29" frame="punct(punt)" his="normal" his_1="normal" id="46" lcat="punct" lemma="." pos="punct" postag="LET()" pt="let" rel="--" root="." sense="." special="punt" word="."/>
  </node>
  <sentence sentid="4">Als de regering-Trump de soevereiniteit van Turkije niet respecteert , kan onze samenwerking in gevaar zijn , schreef Erdogan vrijdagavond in een gastbijdrage in de New York Times .</sentence>
  <comments>
    <comment>Q#4|Als de regering-Trump de soevereiniteit van Turkije niet respecteert , kan onze samenwerking in gevaar zijn , schreef Erdogan vrijdagavond in een gastbijdrage in de New York Times .|1|1|-5.964696619659996</comment>
  </comments>
</alpino_ds>
