<?xml version="1.0" encoding="UTF-8"?>
<alpino_ds version="1.6">
  <parser cats="1" skips="0" />
  <node begin="0" cat="top" end="8" id="0" rel="top">
    <node begin="2" end="3" frame="punct(dubb_punt)" his="normal" his_1="normal" id="1" lcat="punct" lemma=":" pos="punct" postag="LET()" pt="let" rel="--" root=":" sense=":" special="dubb_punt" word=":"/>
    <node begin="5" end="6" frame="punct(komma)" his="normal" his_1="normal" id="2" lcat="punct" lemma="," pos="punct" postag="LET()" pt="let" rel="--" root="," sense="," special="komma" word=","/>
    <node begin="0" cat="np" end="8" id="3" rel="--">
      <node aform="base" begin="0" buiging="met-e" end="1" frame="adjective(e)" graad="basis" his="normal" his_1="normal" id="4" infl="e" lcat="ap" lemma="Vlaams" naamval="stan" pos="adj" positie="prenom" postag="ADJ(prenom,basis,met-e,stan)" pt="adj" rel="mod" root="Vlaams" sense="Vlaams" vform="adj" word="Vlaamse"/>
      <node begin="1" end="2" frame="noun(de,count,sg)" gen="de" genus="zijd" getal="ev" graad="basis" his="compound" his_1="2" id="5" lcat="np" lemma="super_minister_raad" naamval="stan" ntype="soort" num="sg" pos="noun" postag="N(soort,ev,basis,zijd,stan)" pt="n" rel="hd" rnum="sg" root="super_minister_raad" sense="super_minister_raad" word="superministerraad"/>
      <node begin="3" cat="conj" end="8" id="6" rel="app">
        <node begin="3" cat="np" end="5" id="7" rel="cnj">
          <node aform="base" begin="3" buiging="zonder" end="4" frame="adjective(no_e(odet_adv))" graad="basis" his="normal" his_1="normal" id="8" infl="no_e" lcat="ap" lemma="veel" naamval="stan" npagr="agr" pdtype="grad" pos="adj" positie="prenom" postag="VNW(onbep,grad,stan,prenom,zonder,agr,basis)" pt="vnw" rel="det" root="veel" sense="veel" vform="adj" vwtype="onbep" word="veel"/>
          <node begin="4" end="5" frame="noun(het,count,pl)" gen="het" getal="mv" graad="basis" his="normal" his_1="normal" id="9" lcat="np" lemma="plan" ntype="soort" num="pl" pos="noun" postag="N(soort,mv,basis)" pt="n" rel="hd" rnum="pl" root="plan" sense="plan" word="plannen"/>
        </node>
        <node begin="6" cat="np" end="8" id="10" rel="cnj">
          <node aform="base" begin="6" buiging="zonder" end="7" frame="adjective(no_e(odet_adv))" graad="basis" his="normal" his_1="normal" id="11" infl="no_e" lcat="ap" lemma="weinig" naamval="stan" npagr="agr" pdtype="grad" pos="adj" positie="prenom" postag="VNW(onbep,grad,stan,prenom,zonder,agr,basis)" pt="vnw" rel="det" root="weinig" sense="weinig" vform="adj" vwtype="onbep" word="weinig"/>
          <node begin="7" end="8" frame="noun(de,count,pl)" gen="de" getal="mv" graad="basis" his="normal" his_1="normal" id="12" lcat="np" lemma="beslissing" ntype="soort" num="pl" pos="noun" postag="N(soort,mv,basis)" pt="n" rel="hd" rnum="pl" root="beslissing" sense="beslissing" word="beslissingen"/>
        </node>
      </node>
    </node>
  </node>
  <sentence sentid="1">Vlaamse superministerraad : veel plannen , weinig beslissingen</sentence>
  <comments>
    <comment>Q#1|Vlaamse superministerraad : veel plannen , weinig beslissingen|1|1|-1.4611428209199995</comment>
  </comments>
</alpino_ds>
