<?xml version="1.0" encoding="UTF-8"?>
<alpino_ds version="1.6">
  <parser cats="1" skips="0" />
  <node begin="0" cat="top" end="19" id="0" rel="top">
    <node begin="5" end="6" frame="punct(komma)" his="normal" his_1="normal" id="1" lcat="punct" lemma="," pos="punct" postag="LET()" pt="let" rel="--" root="," sense="," special="komma" word=","/>
    <node begin="0" cat="smain" end="18" id="2" rel="--">
      <node begin="0" cat="conj" end="9" id="3" rel="su">
        <node begin="0" cat="np" end="5" id="4" rel="cnj">
          <node begin="0" end="1" frame="modal_adverb(noun_prep)" his="normal" his_1="decap" his_1_1="normal" id="5" index="1" lcat="advp" lemma="liefst" pos="adv" postag="BW()" pt="bw" rel="mod" root="liefst" sc="noun_prep" sense="liefst" word="Liefst"/>
          <node begin="1" end="2" frame="number(hoofd(pl_num))" his="normal" his_1="normal" id="6" infl="pl_num" lcat="detp" lemma="2.500" naamval="stan" numtype="hoofd" pos="num" positie="prenom" postag="TW(hoofd,prenom,stan)" pt="tw" rel="det" root="2.500" sense="2.500" special="hoofd" word="2.500"/>
          <node begin="2" end="3" frame="noun(het,count,pl)" gen="het" getal="mv" graad="basis" his="compound" his_1="2" id="7" lcat="np" lemma="gevecht_voertuig" ntype="soort" num="pl" pos="noun" postag="N(soort,mv,basis)" pt="n" rel="hd" rnum="pl" root="gevecht_voertuig" sense="gevecht_voertuig" word="gevechtsvoertuigen"/>
          <node begin="3" cat="cp" end="5" id="8" rel="mod">
            <node begin="3" conjtype="onder" end="4" frame="complementizer(zoals)" his="normal" his_1="normal" id="9" lcat="cp" lemma="zoals" pos="comp" postag="VG(onder)" pt="vg" rel="cmp" root="zoals" sc="zoals" sense="zoals" word="zoals"/>
            <node begin="4" end="5" frame="noun(de,count,pl)" gen="de" getal="mv" graad="basis" his="normal" his_1="normal" id="10" lcat="np" lemma="tank" ntype="soort" num="pl" pos="noun" postag="N(soort,mv,basis)" pt="n" rel="body" rnum="pl" root="tank" sense="tank" word="tanks"/>
          </node>
        </node>
        <node begin="0" cat="np" end="7" id="11" rel="cnj">
          <node begin="0" end="1" id="12" index="1" rel="mod"/>
          <node begin="6" end="7" frame="noun(de,count,pl)" gen="de" getal="mv" graad="basis" his="normal" his_1="normal" id="13" lcat="np" lemma="pantser_wagen" ntype="soort" num="pl" pos="noun" postag="N(soort,mv,basis)" pt="n" rel="hd" rnum="pl" root="pantser_wagen" sense="pantser_wagen" word="pantserwagens"/>
        </node>
        <node begin="7" conjtype="neven" end="8" frame="conj(en)" his="normal" his_1="normal" id="14" lcat="vg" lemma="en" pos="vg" postag="VG(neven)" pt="vg" rel="crd" root="en" sense="en" word="en"/>
        <node begin="0" cat="np" end="9" id="15" rel="cnj">
          <node begin="0" end="1" id="16" index="1" rel="mod"/>
          <node begin="8" end="9" frame="noun(de,count,pl)" gen="de" getal="mv" graad="basis" his="normal" his_1="normal" id="17" lcat="np" lemma="jeep" ntype="soort" num="pl" pos="noun" postag="N(soort,mv,basis)" pt="n" rel="hd" rnum="pl" root="jeep" sense="jeep" word="jeeps"/>
        </node>
      </node>
      <node begin="9" end="10" frame="verb(unacc,pl,ld_pp)" his="normal" his_1="normal" id="18" infl="pl" lcat="smain" lemma="vertrekken" pos="verb" postag="WW(pv,tgw,mv)" pt="ww" pvagr="mv" pvtijd="tgw" rel="hd" root="vertrek" sc="ld_pp" sense="vertrek" stype="declarative" tense="present" word="vertrekken" wvorm="pv"/>
      <node begin="10" cat="np" end="13" id="19" rel="mod">
        <node begin="10" end="11" frame="determiner(de)" his="normal" his_1="normal" id="20" infl="de" lcat="detp" lemma="de" lwtype="bep" naamval="stan" npagr="rest" pos="det" postag="LID(bep,stan,rest)" pt="lid" rel="det" root="de" sense="de" word="de"/>
        <node aform="base" begin="11" buiging="met-e" end="12" frame="adjective(ende(padv))" his="normal" his_1="V-de" his_1_1="normal" id="21" infl="e" lcat="ppres" lemma="komen" pos="adj" positie="prenom" postag="WW(od,prenom,met-e)" pt="ww" rel="mod" root="kom" sense="kom" vform="gerund" word="komende" wvorm="od"/>
        <node begin="12" end="13" frame="tmp_noun(de,count,pl)" gen="de" getal="mv" graad="basis" his="normal" his_1="normal" id="22" lcat="np" lemma="dag" ntype="soort" num="pl" pos="noun" postag="N(soort,mv,basis)" pt="n" rel="hd" rnum="pl" root="dag" sense="dag" special="tmp" word="dagen"/>
      </node>
      <node begin="13" cat="pp" end="16" id="23" rel="mod">
        <node begin="13" end="14" frame="preposition(vanuit,[])" his="normal" his_1="normal" id="24" lcat="pp" lemma="vanuit" pos="prep" postag="VZ(init)" pt="vz" rel="hd" root="vanuit" sense="vanuit" vztype="init" word="vanuit"/>
        <node begin="14" cat="np" end="16" id="25" rel="obj1">
          <node begin="14" end="15" frame="determiner(het,nwh,nmod,pro,nparg,wkpro)" his="normal" his_1="normal" id="26" infl="het" lcat="detp" lemma="het" lwtype="bep" naamval="stan" npagr="evon" pos="det" postag="LID(bep,stan,evon)" pt="lid" rel="det" root="het" sense="het" wh="nwh" word="het"/>
          <node begin="15" end="16" frame="proper_name(both,'LOC')" genus="onz" getal="ev" graad="basis" his="name" his_1="not_begin" id="27" lcat="np" lemma="Vrasenedok" naamval="stan" neclass="LOC" ntype="eigen" num="both" pos="name" postag="N(eigen,ev,basis,onz,stan)" pt="n" rel="hd" rnum="sg" root="Vrasenedok" sense="Vrasenedok" word="Vrasenedok"/>
        </node>
      </node>
      <node begin="16" cat="pp" end="18" id="28" rel="ld">
        <node begin="16" end="17" frame="preposition(naar,[toe])" his="normal" his_1="normal" id="29" lcat="pp" lemma="naar" pos="prep" postag="VZ(init)" pt="vz" rel="hd" root="naar" sense="naar" vztype="init" word="naar"/>
        <node begin="17" end="18" frame="proper_name(sg,'LOC')" genus="onz" getal="ev" graad="basis" his="normal" his_1="names_dictionary" id="30" lcat="np" lemma="Polen" naamval="stan" neclass="LOC" ntype="eigen" num="sg" pos="name" postag="N(eigen,ev,basis,onz,stan)" pt="n" rel="obj1" rnum="sg" root="Polen" sense="Polen" word="Polen"/>
      </node>
    </node>
    <node begin="18" end="19" frame="punct(punt)" his="normal" his_1="normal" id="31" lcat="punct" lemma="." pos="punct" postag="LET()" pt="let" rel="--" root="." sense="." special="punt" word="."/>
  </node>
  <sentence sentid="3">Liefst 2.500 gevechtsvoertuigen zoals tanks , pantserwagens en jeeps vertrekken de komende dagen vanuit het Vrasenedok naar Polen .</sentence>
  <comments>
    <comment>Q#3|Liefst 2.500 gevechtsvoertuigen zoals tanks , pantserwagens en jeeps vertrekken de komende dagen vanuit het Vrasenedok naar Polen .|1|1|-9.718208001250002</comment>
  </comments>
</alpino_ds>
