<?xml version="1.0" encoding="UTF-8"?>
<alpino_ds version="1.6">
  <parser cats="1" skips="0" />
  <node begin="0" cat="top" end="22" id="0" rel="top">
    <node begin="9" end="10" frame="punct(komma)" his="normal" his_1="normal" id="1" lcat="punct" lemma="," pos="punct" postag="LET()" pt="let" rel="--" root="," sense="," special="komma" word=","/>
    <node begin="16" end="17" frame="punct(komma)" his="normal" his_1="normal" id="2" lcat="punct" lemma="," pos="punct" postag="LET()" pt="let" rel="--" root="," sense="," special="komma" word=","/>
    <node begin="0" cat="conj" end="21" id="3" rel="--">
      <node begin="0" cat="smain" end="9" id="4" rel="cnj">
        <node begin="1" end="2" frame="verb(unacc,sg3,te_passive)" his="normal" his_1="normal" id="5" infl="sg3" lcat="smain" lemma="vallen" pos="verb" postag="WW(pv,tgw,met-t)" pt="ww" pvagr="met-t" pvtijd="tgw" rel="hd" root="val" sc="te_passive" sense="val" stype="declarative" tense="present" word="valt" wvorm="pv"/>
        <node begin="3" cat="np" end="5" id="6" index="1" rel="su">
          <node begin="3" buiging="zonder" end="4" frame="determiner(geen,nwh,mod,pro,yparg,nwkpro,geen)" his="normal" his_1="normal" id="7" infl="geen" lcat="detp" lemma="geen" naamval="stan" npagr="agr" pdtype="det" pos="det" positie="prenom" postag="VNW(onbep,det,stan,prenom,zonder,agr)" pt="vnw" rel="det" root="geen" sense="geen" vwtype="onbep" wh="nwh" word="geen"/>
          <node begin="4" end="5" frame="noun(de,count,sg)" gen="de" genus="zijd" getal="ev" graad="basis" his="normal" his_1="normal" id="8" lcat="np" lemma="speld" naamval="stan" ntype="soort" num="sg" pos="noun" postag="N(soort,ev,basis,zijd,stan)" pt="n" rel="hd" rnum="sg" root="speld" sense="speld" word="speld"/>
        </node>
        <node begin="0" cat="ti" end="9" id="9" rel="vc">
          <node begin="7" end="8" frame="complementizer(te)" his="normal" his_1="normal" id="10" lcat="ti" lemma="te" pos="comp" postag="VZ(init)" pt="vz" rel="cmp" root="te" sc="te" sense="te" vztype="init" word="te"/>
          <node begin="0" cat="inf" end="9" id="11" rel="body">
            <node aform="base" begin="0" buiging="zonder" end="1" frame="adjective(no_e(adv))" graad="basis" his="normal" his_1="decap" his_1_1="normal" id="12" infl="no_e" lcat="ap" lemma="juridisch" pos="adj" positie="vrij" postag="ADJ(vrij,basis,zonder)" pt="adj" rel="mod" root="juridisch" sense="juridisch" vform="adj" word="Juridisch"/>
            <node begin="3" end="5" id="13" index="1" rel="obj1"/>
            <node aform="compar" begin="5" buiging="zonder" end="6" frame="adjective(meer)" graad="comp" his="normal" his_1="normal" id="14" infl="meer" lcat="ap" lemma="meer" naamval="stan" pdtype="grad" pos="adj" positie="vrij" postag="VNW(onbep,grad,stan,vrij,zonder,comp)" pt="vnw" rel="mod" root="meer" sense="meer" vform="adj" vwtype="onbep" word="meer"/>
            <node begin="2" cat="pp" end="7" id="15" rel="ld">
              <node begin="2" end="3" frame="er_loc_adverb" getal="getal" his="normal" his_1="normal" id="16" lcat="advp" lemma="daar" naamval="obl" pdtype="adv-pron" persoon="3o" pos="adv" postag="VNW(aanw,adv-pron,obl,vol,3o,getal)" pt="vnw" rel="obj1" root="daar" sense="daar" special="er_loc" status="vol" vwtype="aanw" word="daar"/>
              <node begin="6" end="7" frame="preposition(tussen,[door,in,vandaan])" his="normal" his_1="normal" id="17" lcat="pp" lemma="tussen" pos="prep" postag="VZ(fin)" pt="vz" rel="hd" root="tussen" sense="tussen" vztype="fin" word="tussen"/>
            </node>
            <node begin="8" buiging="zonder" end="9" frame="verb(hebben,inf,np_ld_pp)" his="normal" his_1="normal" id="18" infl="inf" lcat="inf" lemma="krijgen" pos="verb" positie="vrij" postag="WW(inf,vrij,zonder)" pt="ww" rel="hd" root="krijg" sc="np_ld_pp" sense="krijg" word="krijgen" wvorm="inf"/>
          </node>
        </node>
      </node>
      <node begin="10" conjtype="neven" end="11" frame="conj(maar)" his="normal" his_1="normal" id="19" lcat="vg" lemma="maar" pos="vg" postag="VG(neven)" pt="vg" rel="crd" root="maar" sense="maar" word="maar"/>
      <node begin="11" cat="smain" end="21" id="20" rel="cnj">
        <node aform="base" begin="11" buiging="zonder" end="12" frame="adjective(no_e(adv))" graad="basis" his="normal" his_1="normal" id="21" infl="no_e" lcat="ap" lemma="diplomatiek" pos="adj" positie="vrij" postag="ADJ(vrij,basis,zonder)" pt="adj" rel="mod" root="diplomatiek" sense="diplomatiek" vform="adj" word="diplomatiek"/>
        <node begin="12" end="13" frame="verb(hebben,sg3,nonp_copula)" his="normal" his_1="normal" id="22" infl="sg3" lcat="smain" lemma="liggen" pos="verb" postag="WW(pv,tgw,met-t)" pt="ww" pvagr="met-t" pvtijd="tgw" rel="hd" root="lig" sc="nonp_copula" sense="lig" stype="declarative" tense="present" word="ligt" wvorm="pv"/>
        <node begin="13" end="14" frame="determiner(het,nwh,nmod,pro,nparg)" getal="ev" his="normal" his_1="normal" id="23" infl="het" lcat="np" lemma="dat" naamval="stan" pdtype="pron" persoon="3o" pos="det" postag="VNW(aanw,pron,stan,vol,3o,ev)" pt="vnw" rel="su" rnum="sg" root="dat" sense="dat" status="vol" vwtype="aanw" wh="nwh" word="dat"/>
        <node begin="14" cat="ap" end="21" id="24" rel="predc">
          <node aform="base" begin="14" buiging="zonder" end="15" frame="adjective(no_e(adv))" graad="basis" his="normal" his_1="normal" id="25" infl="no_e" lcat="ap" lemma="bijzonder" pos="adj" positie="vrij" postag="ADJ(vrij,basis,zonder)" pt="adj" rel="mod" root="bijzonder" sense="bijzonder" vform="adj" word="bijzonder"/>
          <node aform="base" begin="15" buiging="zonder" end="16" frame="adjective(no_e(adv),pp(voor))" graad="basis" his="normal" his_1="normal" id="26" infl="no_e" lcat="ap" lemma="gevoelig" pos="adj" positie="vrij" postag="ADJ(vrij,basis,zonder)" pt="adj" rel="hd" root="gevoelig" sc="pp(voor)" sense="gevoelig-voor" vform="adj" word="gevoelig"/>
          <node begin="17" cat="pp" end="21" id="27" rel="pc">
            <node begin="17" buiging="zonder" end="18" frame="modal_adverb" graad="basis" his="normal" his_1="normal" id="28" lcat="advp" lemma="zeker" pos="adv" positie="vrij" postag="ADJ(vrij,basis,zonder)" pt="adj" rel="mod" root="zeker" sc="modal" sense="zeker" word="zeker"/>
            <node begin="18" end="19" frame="preposition(voor,[aan,door,uit,[in,de,plaats]])" his="normal" his_1="normal" id="29" lcat="pp" lemma="voor" pos="prep" postag="VZ(init)" pt="vz" rel="hd" root="voor" sense="voor" vztype="init" word="voor"/>
            <node begin="19" cat="np" end="21" id="30" rel="obj1">
              <node begin="19" end="20" frame="determiner(de)" his="normal" his_1="normal" id="31" infl="de" lcat="detp" lemma="de" lwtype="bep" naamval="stan" npagr="rest" pos="det" postag="LID(bep,stan,rest)" pt="lid" rel="det" root="de" sense="de" word="de"/>
              <node aform="base" begin="20" buiging="met-e" end="21" frame="nominalized_adjective" getal-n="mv-n" graad="basis" his="normal" his_1="normal" id="32" lcat="np" lemma="Franstalig" num="pl" personalized="true" pos="adj" positie="nom" postag="ADJ(nom,basis,met-e,mv-n)" pt="adj" rel="hd" rnum="pl" root="Franstalig" sense="Franstalig" special="a_noun" word="Franstaligen"/>
            </node>
          </node>
        </node>
      </node>
    </node>
    <node begin="21" end="22" frame="punct(punt)" his="normal" his_1="normal" id="33" lcat="punct" lemma="." pos="punct" postag="LET()" pt="let" rel="--" root="." sense="." special="punt" word="."/>
  </node>
  <sentence sentid="3">Juridisch valt daar geen speld meer tussen te krijgen , maar diplomatiek ligt dat bijzonder gevoelig , zeker voor de Franstaligen .</sentence>
  <comments>
    <comment>Q#3|Juridisch valt daar geen speld meer tussen te krijgen , maar diplomatiek ligt dat bijzonder gevoelig , zeker voor de Franstaligen .|1|1|-6.661864624069992</comment>
  </comments>
</alpino_ds>
